{
  "updated_at": "2026-07-22T17:26:19.696128Z",
  "radar_scanned_at": "2026-07-21T21:34:46.426980Z",
  "quotes": {
    "NET": {
      "price": 270.745,
      "prev_close": 271.3,
      "chg_pct": -0.2,
      "pre": null,
      "pre_pct": null,
      "post": null,
      "post_pct": null,
      "session": "regular",
      "as_of": "2026-07-22T17:25:39.510319Z"
    },
    "PANW": {
      "price": 336.975,
      "prev_close": 341.845,
      "chg_pct": -1.42,
      "pre": null,
      "pre_pct": null,
      "post": null,
      "post_pct": null,
      "session": "regular",
      "as_of": "2026-07-22T17:25:40.725261Z"
    },
    "1398.HK": {
      "price": 7.0,
      "prev_close": 7.02,
      "chg_pct": -0.28,
      "pre": null,
      "pre_pct": null,
      "post": null,
      "post_pct": null,
      "session": "closed",
      "as_of": "2026-07-22T17:25:41.734337Z"
    },
    "0002.HK": {
      "price": 77.5,
      "prev_close": 76.75,
      "chg_pct": 0.98,
      "pre": null,
      "pre_pct": null,
      "post": null,
      "post_pct": null,
      "session": "closed",
      "as_of": "2026-07-22T17:25:42.555552Z"
    },
    "0001.HK": {
      "price": 71.45,
      "prev_close": 71.35,
      "chg_pct": 0.14,
      "pre": null,
      "pre_pct": null,
      "post": null,
      "post_pct": null,
      "session": "closed",
      "as_of": "2026-07-22T17:25:43.605128Z"
    },
    "AMZN": {
      "price": 243.225,
      "prev_close": 246.79,
      "chg_pct": -1.44,
      "pre": null,
      "pre_pct": null,
      "post": null,
      "post_pct": null,
      "session": "regular",
      "as_of": "2026-07-22T17:25:44.420360Z"
    },
    "2057.HK": {
      "price": 188.4,
      "prev_close": 189.8,
      "chg_pct": -0.74,
      "pre": null,
      "pre_pct": null,
      "post": null,
      "post_pct": null,
      "session": "closed",
      "as_of": "2026-07-22T17:25:45.256051Z"
    },
    "2388.HK": {
      "price": 47.42,
      "prev_close": 47.06,
      "chg_pct": 0.76,
      "pre": null,
      "pre_pct": null,
      "post": null,
      "post_pct": null,
      "session": "closed",
      "as_of": "2026-07-22T17:25:46.224074Z"
    },
    "XOM": {
      "price": 154.37,
      "prev_close": 151.7501,
      "chg_pct": 1.73,
      "pre": null,
      "pre_pct": null,
      "post": null,
      "post_pct": null,
      "session": "regular",
      "as_of": "2026-07-22T17:25:47.204939Z"
    },
    "NVDA": {
      "price": 213.7,
      "prev_close": 206.35,
      "chg_pct": 3.56,
      "pre": null,
      "pre_pct": null,
      "post": null,
      "post_pct": null,
      "session": "regular",
      "as_of": "2026-07-22T17:25:48.064988Z"
    },
    "CVX": {
      "price": 192.876,
      "prev_close": 190.94,
      "chg_pct": 1.01,
      "pre": null,
      "pre_pct": null,
      "post": null,
      "post_pct": null,
      "session": "closed",
      "as_of": "2026-07-22T17:26:18.716646Z"
    },
    "0941.HK": {
      "price": 80.55,
      "prev_close": 80.7,
      "chg_pct": -0.19,
      "pre": null,
      "pre_pct": null,
      "post": null,
      "post_pct": null,
      "session": "closed",
      "as_of": "2026-07-22T17:26:19.696113Z"
    }
  }
}